hcl2_ast/__init__.py
hcl2_ast/__main__.py
hcl2_ast/api.py
hcl2_ast/ast.py
hcl2_ast/parse.py
hcl2_ast/py.typed
hcl2_ast/transformer.py
hcl2_ast-0.4.0.dist-info/LICENSE
hcl2_ast-0.4.0.dist-info/WHEEL
hcl2_ast-0.4.0.dist-info/METADATA
hcl2_ast-0.4.0.dist-info/RECORD
