Metadata-Version: 2.1
Name: hcl2-ast
Version: 0.4.0
Summary: 
License: MIT
Author: Niklas Rosenstein
Author-email: rosensteinniklas@gmail.com
Requires-Python: >=3.6,<4.0
Classifier: License :: OSI Approved :: MIT License
Classifier: Programming Language :: Python :: 3
Classifier: Programming Language :: Python :: 3.6
Classifier: Programming Language :: Python :: 3.7
Classifier: Programming Language :: Python :: 3.8
Classifier: Programming Language :: Python :: 3.9
Classifier: Programming Language :: Python :: 3.10
Requires-Dist: python-hcl2 (>=3.0.5,<4.0.0)
Requires-Dist: termcolor (>=1.1.0,<2.0.0)
Requires-Dist: typing-extensions (>=3.10.0)
Project-URL: Bug Tracker, https://github.com/NiklasRosenstein/python-hcl2-ast/issues
Project-URL: Repository, https://github.com/NiklasRosenstein/python-hcl2-ast
